odoo10_addon_hr_language-10.0.0.1.0.99.dev14-py3.8-nspkg.pth
odoo/addons/hr_language/README.rst
odoo/addons/hr_language/__init__.py
odoo/addons/hr_language/__manifest__.py
odoo/addons/hr_language/i18n/ar.po
odoo/addons/hr_language/i18n/cs_CZ.po
odoo/addons/hr_language/i18n/de.po
odoo/addons/hr_language/i18n/es.po
odoo/addons/hr_language/i18n/fi.po
odoo/addons/hr_language/i18n/fr.po
odoo/addons/hr_language/i18n/hr.po
odoo/addons/hr_language/i18n/hr_HR.po
odoo/addons/hr_language/i18n/hr_language.pot
odoo/addons/hr_language/i18n/it.po
odoo/addons/hr_language/i18n/lt.po
odoo/addons/hr_language/i18n/nl_NL.po
odoo/addons/hr_language/i18n/pt_BR.po
odoo/addons/hr_language/i18n/ro.po
odoo/addons/hr_language/i18n/sl.po
odoo/addons/hr_language/models/__init__.py
odoo/addons/hr_language/models/hr_employee.py
odoo/addons/hr_language/models/hr_language.py
odoo/addons/hr_language/security/ir.model.access.csv
odoo/addons/hr_language/static/description/icon.png
odoo/addons/hr_language/views/hr_employee.xml
odoo/addons/hr_language/views/hr_language.xml
odoo10_addon_hr_language-10.0.0.1.0.99.dev14.dist-info/METADATA
odoo10_addon_hr_language-10.0.0.1.0.99.dev14.dist-info/WHEEL
odoo10_addon_hr_language-10.0.0.1.0.99.dev14.dist-info/namespace_packages.txt
odoo10_addon_hr_language-10.0.0.1.0.99.dev14.dist-info/top_level.txt
odoo10_addon_hr_language-10.0.0.1.0.99.dev14.dist-info/RECORD
